lovehim/__init__.py
lovehim/__main__.py
lovehim/get_verse.py
lovehim-0.57.dist-info/METADATA
lovehim-0.57.dist-info/WHEEL
lovehim-0.57.dist-info/entry_points.txt
lovehim-0.57.dist-info/top_level.txt
lovehim-0.57.dist-info/RECORD
